cvglue/__init__.py
cvglue/algorithmn/__init__.py
cvglue/algorithmn/fhog.py
cvglue/algorithmn/kcf_tracker.py
cvglue/checker/__init__.py
cvglue/checker/base.py
cvglue/checker/blur.py
cvglue/checker/face.py
cvglue/checker/landmark.py
cvglue/checker/properties.py
cvglue/checker/sample.py
cvglue/checker/similarity.py
cvglue/checker/virtualface.py
cvglue/detector/__init__.py
cvglue/detector/face.py
cvglue/displayer/__init__.py
cvglue/displayer/iap_visualize.py
cvglue/displayer/ipython.py
cvglue/displayer/matplot.py
cvglue/parser/__init__.py
cvglue/parser/base.py
cvglue/parser/face.py
cvglue/parser/mask.py
cvglue/processor/__init__.py
cvglue/processor/crop.py
cvglue/thirdparty/__init__.py
cvglue/thirdparty/AdaptiveWing/LICENSE
cvglue/thirdparty/AdaptiveWing/README.md
cvglue/thirdparty/AdaptiveWing/__init__.py
cvglue/thirdparty/AdaptiveWing/coord_conv.py
cvglue/thirdparty/AdaptiveWing/interface.py
cvglue/thirdparty/AdaptiveWing/models.py
cvglue/thirdparty/AttributeDetector/__init__.py
cvglue/thirdparty/AttributeDetector/face_model.json
cvglue/thirdparty/AttributeDetector/interface.py
cvglue/thirdparty/AttributeDetector/labels.json
cvglue/thirdparty/AttributeDetector/sklearn_json.py
cvglue/thirdparty/FBCNN/__init__.py
cvglue/thirdparty/FBCNN/comfy_ui_utils.py
cvglue/thirdparty/FBCNN/interface.py
cvglue/thirdparty/FBCNN/model.py
cvglue/thirdparty/FBCNN/official_inference.py
cvglue/thirdparty/FaceDetector/LICENSE
cvglue/thirdparty/FaceDetector/README.md
cvglue/thirdparty/FaceDetector/__init__.py
cvglue/thirdparty/FaceDetector/calculate_paremeter_flop.py
cvglue/thirdparty/FaceDetector/convert_to_onnx.py
cvglue/thirdparty/FaceDetector/detect.py
cvglue/thirdparty/FaceDetector/interface.py
cvglue/thirdparty/FaceDetector/test_widerface.py
cvglue/thirdparty/FaceDetector/train.py
cvglue/thirdparty/FaceDetector/Face_Detector_ncnn/.gitignore
cvglue/thirdparty/FaceDetector/Face_Detector_ncnn/CMakeLists.txt
cvglue/thirdparty/FaceDetector/Face_Detector_ncnn/FaceDetector.cpp
cvglue-1.1.0.dist-info/METADATA
cvglue-1.1.0.dist-info/WHEEL
cvglue-1.1.0.dist-info/licenses/LICENSE
cvglue-1.1.0.dist-info/RECORD
