Metadata-Version: 2.4
Name: cvglue
Version: 1.1.0
Summary: Glue tools of computer vision
Project-URL: Homepage, https://github.com/Lamply/CVGlue
Project-URL: Issues, https://github.com/Lamply/CVGlue/issues
Author-email: Lamply <lamplykyz@gmail.com>
License-Expression: MIT
License-File: LICENSE
Keywords: computer vision
Classifier: Operating System :: OS Independent
Classifier: Programming Language :: Python :: 3
Requires-Python: >=3.6
Requires-Dist: albumentations>=1.1.0
Requires-Dist: deepdiff
Requires-Dist: imageio-ffmpeg
Requires-Dist: ipython
Requires-Dist: lpips
Requires-Dist: matplotlib
Requires-Dist: numpy
Requires-Dist: onnx
Requires-Dist: onnxruntime-gpu
Requires-Dist: opencv-python
Requires-Dist: pytest
Requires-Dist: requests
Requires-Dist: scikit-image
Requires-Dist: scikit-learn
Requires-Dist: termcolor
Requires-Dist: torch>=1.6.0
Provides-Extra: option1
Requires-Dist: face-recognition; extra == 'option1'
Requires-Dist: insightface; extra == 'option1'
